sp110e/__init__.py
sp110e/controller.py
sp110e/controller_sync.py
sp110e/driver.py
sp110e-1.4.2.dist-info/LICENSE
sp110e-1.4.2.dist-info/WHEEL
sp110e-1.4.2.dist-info/METADATA
sp110e-1.4.2.dist-info/RECORD
