Metadata-Version: 2.1
Name: sp110e
Version: 1.4.2
Summary: Control SP110E BLE RGB LED device from computer
Home-page: https://github.com/roslovets/SP110E
License: MIT
Keywords: SP110E,RGB,LED
Author: Pavel Roslovets
Author-email: p.v.roslovets@gmail.com
Requires-Python: >=3.7,<4.0
Classifier: License :: OSI Approved :: MIT License
Classifier: Operating System :: OS Independent
Classifier: Programming Language :: Python :: 3
Classifier: Programming Language :: Python :: 3.7
Classifier: Programming Language :: Python :: 3.8
Classifier: Programming Language :: Python :: 3.9
Classifier: Programming Language :: Python :: 3.10
Classifier: Programming Language :: Python :: 3
Requires-Dist: bleak (>=0.15.1)
Requires-Dist: syncer (==1.3.0)
Project-URL: Repository, https://github.com/roslovets/SP110E
